puppet_tools/__init__.py
puppet_tools/__main__.py
puppet_tools/constants.py
puppet_tools/main.py
puppet_tools/parser.py
puppet_tools/utility.py
puppet_tools/validate.py
puppet_tools/puppet_objects/__init__.py
puppet_tools/puppet_objects/puppet_block.py
puppet_tools/puppet_objects/puppet_case.py
puppet_tools/puppet_objects/puppet_case_item.py
puppet_tools/puppet_objects/puppet_class.py
puppet_tools/puppet_objects/puppet_file.py
puppet_tools/puppet_objects/puppet_include.py
puppet_tools/puppet_objects/puppet_resource.py
puppet_tools/puppet_objects/puppet_variable.py
Puppet_Tools-0.0.5.dist-info/LICENSE
Puppet_Tools-0.0.5.dist-info/METADATA
Puppet_Tools-0.0.5.dist-info/WHEEL
Puppet_Tools-0.0.5.dist-info/entry_points.txt
Puppet_Tools-0.0.5.dist-info/top_level.txt
Puppet_Tools-0.0.5.dist-info/RECORD
